django_simple_csp/__init__.py
django_simple_csp/middleware/__init__.py
django_simple_csp/middleware/csp.py
django_simple_csp/templatetags/__init__.py
django_simple_csp/templatetags/csp.py
django_simple_csp-0.5.dev1.dist-info/METADATA
django_simple_csp-0.5.dev1.dist-info/WHEEL
django_simple_csp-0.5.dev1.dist-info/licenses/LICENSE
django_simple_csp-0.5.dev1.dist-info/RECORD
