Metadata-Version: 2.4
Name: django-simple-csp
Version: 0.5.dev1
Summary: Django Content Security Policy support.
Project-URL: Repository, https://github.com/fsinfuhh/django-simple-csp
Project-URL: Issues, https://github.com/fsinfuhh/django-simple-csp/issues
Author: Henning Pridöhl
Author-email: Nils Rokita <github@rokita.it>
Maintainer-email: Nils Rokita <github@rokita.it>
License-Expression: MIT
License-File: LICENSE
Keywords: CSP,Content-Security-Policy,Django
Classifier: Development Status :: 3 - Alpha
Classifier: Environment :: Web Environment
Classifier: Framework :: Django
Classifier: Intended Audience :: Developers
Classifier: License :: OSI Approved :: MIT License
Classifier: Operating System :: OS Independent
Classifier: Programming Language :: Python
Classifier: Programming Language :: Python :: 3
Classifier: Programming Language :: Python :: 3.6
Classifier: Topic :: Software Development :: Libraries :: Python Modules
Requires-Python: >=3.6
Requires-Dist: django>=1.11
